{
  "_": 0,
  "iy": 1,
  "ih": 2,
  "ix": 2,
  "eh": 3,
  "ae": 4,
  "ah": 5,
  "ax": 5,
  "ax-h": 5,
  "uw": 6,
  "ux": 6,
  "uh": 7,
  "aa": 8,
  "ao": 8,
  "ey": 9,
  "ay": 10,
  "oy": 11,
  "aw": 12,
  "ow": 13,
  "er": 14,
  "axr": 14,
  "l": 15,
  "el": 15,
  "r": 16,
  "w": 17,
  "y": 18,
  "m": 19,
  "em": 19,
  "n": 20,
  "en": 20,
  "nx": 20,
  "ng": 21,
  "eng": 21,
  "dx": 22,
  "jh": 23,
  "ch": 24,
  "z": 25,
  "s": 26,
  "sh": 27,
  "zh": 27,
  "hh": 28,
  "hv": 28,
  "v": 29,
  "f": 30,
  "dh": 31,
  "th": 32,
  "b": 33,
  "p": 34,
  "d": 35,
  "t": 36,
  "g": 37,
  "k": 38,
  "bcl": 39,
  "pcl": 39,
  "dcl": 39,
  "tcl": 39,
  "gcl": 39,
  "kcl": 39,
  "epi": 39,
  "pau": 39,
  "h": 39,
  "q": 39,
  "<s>": 40,
  "</s>": 41
}